[
    {
        "symbol": "NVDA",
        "name": "NVIDIA Corporation",
        "price": "191.52",
        "change": "+1.27"
    },
    {
        "symbol": "MSFT",
        "name": "Microsoft Corporation",
        "price": "481.63",
        "change": "+29.59"
    },
    {
        "symbol": "AAPL",
        "name": "Apple Inc.",
        "price": "256.44",
        "change": "-0.35"
    },
    {
        "symbol": "GOOGL",
        "name": "Alphabet Inc.",
        "price": "336.01",
        "change": "-5.38"
    },
    {
        "symbol": "AMZN",
        "name": "Amazon.com, Inc.",
        "price": "243.01",
        "change": "+1.57"
    },
    {
        "symbol": "META",
        "name": "Meta Platforms, Inc.",
        "price": "668.73",
        "change": "-44.27"
    },
    {
        "symbol": "AVGO",
        "name": "Broadcom Inc.",
        "price": "333.24",
        "change": "+1.10"
    },
    {
        "symbol": "TSM",
        "name": "Taiwan Semiconductor Manufactur",
        "price": "342.30",
        "change": "+0.55"
    },
    {
        "symbol": "TSLA",
        "name": "Tesla, Inc.",
        "price": "431.46",
        "change": "-8.30"
    },
    {
        "symbol": "LLY",
        "name": "Eli Lilly and Company",
        "price": "1,023.80",
        "change": "+4.92"
    },
    {
        "symbol": "0700.HK",
        "name": "TENCENT",
        "price": "622.00",
        "change": "+1.00"
    },
    {
        "symbol": "1299.HK",
        "name": "AIA",
        "price": "90.95",
        "change": "+2.10"
    },
    {
        "symbol": "0005.HK",
        "name": "HSBC HOLDINGS",
        "price": "137.60",
        "change": "+0.10"
    },
    {
        "symbol": "0941.HK",
        "name": "CHINA MOBILE",
        "price": "80.90",
        "change": "+0.00"
    },
    {
        "symbol": "0883.HK",
        "name": "CNOOC",
        "price": "24.98",
        "change": "+0.32"
    },
    {
        "symbol": "0857.HK",
        "name": "PETROCHINA",
        "price": "9.39",
        "change": "+0.14"
    },
    {
        "symbol": "3988.HK",
        "name": "BANK OF CHINA",
        "price": "4.76",
        "change": "+0.09"
    },
    {
        "symbol": "1398.HK",
        "name": "ICBC",
        "price": "6.64",
        "change": "+0.05"
    },
    {
        "symbol": "0939.HK",
        "name": "CCB",
        "price": "8.16",
        "change": "+0.13"
    },
    {
        "symbol": "3690.HK",
        "name": "MEITUAN-W",
        "price": "98.60",
        "change": "+0.25"
    }
]